anchorboosting/__init__.py
anchorboosting/models.py
anchorboosting/simulate.py
anchorboosting-0.3.0.dist-info/licenses/LICENSE
anchorboosting-0.3.0.dist-info/METADATA
anchorboosting-0.3.0.dist-info/WHEEL
anchorboosting-0.3.0.dist-info/top_level.txt
anchorboosting-0.3.0.dist-info/RECORD
