Metadata-Version: 2.4
Name: anchorboosting
Version: 0.3.0
Summary: Efficient tree-based nonlinear anchor regression and classification
Author-email: Malte Londschien <malte@londschien.ch>
Project-URL: homepage, https://github.com/mlondschien/anchorboosting/
Classifier: Programming Language :: Python
Requires-Python: >=3.9
License-File: LICENSE
Requires-Dist: numpy
Requires-Dist: scipy
Requires-Dist: lightgbm
Dynamic: license-file
